{"bg": "6B_bg.jpg", "terrain": [{"shape": [205, 298, 514, 426, 256, 440]}, {"shape": [22, 228, 233, 323, 102, 395]}, {"shape": [324, 372, 584, 241, 620, 389]}], "player": {"body.damping": 0, "friction": 0.85, "jump": 450, "depth": 25, "dpeth": "", "speed": 300}, "lvl": "6B", "audio": {"jump": "", "win": "", "lose": "jump.wav"}, "sprites": [{"y": 182, "x": 330, "data": {"": "", "scale": 1, "frame_rate": 12, "img_width": 0, "height": 64, "width": 64, "depth": 25, "img_height": 64, "centerX": 31, "centerY": 31, "frames": 1, "r": 32, "type": "player"}, "key": "blue_guy.png"}, {"y": 240, "x": 219, "data": {"scale": 1, "centerX": 32, "img_width": 256, "height": 64, "width": 64, "depth": 20, "img_height": 64, "frame_rate": 12, "centerY": 33, "frames": 4, "r": 32, "type": "ghost"}, "key": "aniball.png"}, {"y": 275, "x": 379, "data": {"scale": 1, "frame_rate": 12, "jump_interval": 50, "speed": 100, "fall": true, "img_width": 0, "height": 28, "jump": 0, "width": 28, "depth": 15, "img_height": 64, "centerX": 24, "centerY": 16, "frames": 1, "climb": 0.7, "r": 14, "type": "walk"}, "key": "ball.png"}, {"y": 264, "x": 316, "data": {"scale": 1, "img_width": 240, "offsetX": 0, "offsetY": 17, "height": 47, "width": 33, "depth": 30, "img_height": 64, "frame_rate": 12, "frames": 5, "type": "ghost"}, "key": "aniblock.png"}]}